fastjsonschema/__init__.py
fastjsonschema/__main__.py
fastjsonschema/draft04.py
fastjsonschema/draft06.py
fastjsonschema/draft07.py
fastjsonschema/exceptions.py
fastjsonschema/generator.py
fastjsonschema/indent.py
fastjsonschema/ref_resolver.py
fastjsonschema/version.py
fastjsonschema-2.19.0.dist-info/AUTHORS
fastjsonschema-2.19.0.dist-info/LICENSE
fastjsonschema-2.19.0.dist-info/METADATA
fastjsonschema-2.19.0.dist-info/WHEEL
fastjsonschema-2.19.0.dist-info/top_level.txt
fastjsonschema-2.19.0.dist-info/RECORD
